panegyric/__init__.py
panegyric/text.py
Panegyric-0.1.0.dist-info/METADATA
Panegyric-0.1.0.dist-info/WHEEL
Panegyric-0.1.0.dist-info/entry_points.txt
Panegyric-0.1.0.dist-info/top_level.txt
Panegyric-0.1.0.dist-info/RECORD
