Metadata-Version: 2.1
Name: Panegyric
Version: 0.1.0
Summary: Automated compliments via text
Home-page: https://github.com/edwardtheharris/panegyric
Author: Xander Harris
Author-email: xandertheharris@gmail.com
License: UNKNOWN
Project-URL: Bug Tracker, https://github.com/edwardtheharris/panegyric/issues
Platform: UNKNOWN
Requires-Dist: python-dotenv
Requires-Dist: requests
Requires-Dist: ruamel.yaml
